conanpro/__init__.py
conanpro/_modidx.py
conanpro/core.py
conanpro-0.0.1.dist-info/LICENSE
conanpro-0.0.1.dist-info/METADATA
conanpro-0.0.1.dist-info/WHEEL
conanpro-0.0.1.dist-info/entry_points.txt
conanpro-0.0.1.dist-info/top_level.txt
conanpro-0.0.1.dist-info/RECORD
