Metadata-Version: 2.1
Name: conanpro
Version: 0.0.1
Summary: Concept for Analytics Processing
Home-page: https://github.com/fenke/conanpro
Author: Fenke Meijer
Author-email: fenkemeijer@gmail.com
License: Apache Software License 2.0
Keywords: nbdev jupyter notebook python
Classifier: Development Status :: 4 - Beta
Classifier: Intended Audience :: Developers
Classifier: Natural Language :: English
Classifier: Programming Language :: Python :: 3.8
Classifier: Programming Language :: Python :: 3.9
Classifier: Programming Language :: Python :: 3.10
Classifier: License :: OSI Approved :: Apache Software License
Requires-Python: >=3.8
License-File: LICENSE
Requires-Dist: python-dateutil
Requires-Dist: pytz
Requires-Dist: numpy
Requires-Dist: pandas
Requires-Dist: scipy
Requires-Dist: scikit-learn
Provides-Extra: dev
Requires-Dist: python-dateutil ; extra == 'dev'
Requires-Dist: pytz ; extra == 'dev'
Requires-Dist: numpy ; extra == 'dev'
Requires-Dist: pandas ; extra == 'dev'
Requires-Dist: scipy ; extra == 'dev'
Requires-Dist: scikit-learn ; extra == 'dev'
Requires-Dist: jupyter ; extra == 'dev'
Requires-Dist: ipywidgets ; extra == 'dev'
Requires-Dist: jupyterlab >4 ; extra == 'dev'
Requires-Dist: jupyter-contrib-nbextensions ; extra == 'dev'
Requires-Dist: jupyterlab-git ; extra == 'dev'
Requires-Dist: jupyterlab-quarto ; extra == 'dev'
